alethiotx/__init__.py
alethiotx/artemis/__init__.py
alethiotx/artemis/utils.py
alethiotx/artemis/chembl/__init__.py
alethiotx/artemis/chembl/query.py
alethiotx/artemis/clinical/__init__.py
alethiotx/artemis/clinical/scores.py
alethiotx/artemis/cv/__init__.py
alethiotx/artemis/cv/pipeline.py
alethiotx/artemis/hgnc/__init__.py
alethiotx/artemis/hgnc/families.py
alethiotx/artemis/mesh/__init__.py
alethiotx/artemis/mesh/get.py
alethiotx/artemis/pathway/__init__.py
alethiotx/artemis/pathway/genes.py
alethiotx/artemis/upset/__init__.py
alethiotx/artemis/upset/plot.py
alethiotx-2.1.4.dist-info/licenses/LICENSE
alethiotx-2.1.4.dist-info/METADATA
alethiotx-2.1.4.dist-info/WHEEL
alethiotx-2.1.4.dist-info/top_level.txt
alethiotx-2.1.4.dist-info/RECORD
