Metadata-Version: 2.4
Name: alethiotx
Version: 2.1.4
Summary: Alethio Therapeutics Python Toolkit
Author-email: Vladimir Kiselev <vlad.kiselev@alethiomics.com>
License: MIT License
Project-URL: Homepage, https://github.com/alethiotx/pypi
Project-URL: Issues, https://github.com/alethiotx/pypi/issues
Keywords: alethiotx,artemis
Classifier: Programming Language :: Python :: 3
Classifier: License :: OSI Approved :: MIT License
Classifier: Operating System :: OS Independent
Requires-Python: >=3.9
License-File: LICENSE
Requires-Dist: requests
Requires-Dist: scikit-learn
Requires-Dist: pandas
Requires-Dist: numpy
Requires-Dist: matplotlib
Requires-Dist: setuptools
Requires-Dist: upsetplot
Requires-Dist: chembl-downloader
Dynamic: license-file
